synthx/__init__.py
synthx/core/__init__.py
synthx/core/dataset.py
synthx/core/result.py
synthx/core/sample.py
synthx/errors/__init__.py
synthx/method.py
synthx/stats/__init__.py
synthx/stats/p.py
synthx-1.6.0.dist-info/METADATA
synthx-1.6.0.dist-info/WHEEL
synthx-1.6.0.dist-info/RECORD
